CHANGES.txt
README.txt
bootstrap.py
buildout.cfg
setup.py
src/plone/__init__.py
src/plone.recipe.zope2install.egg-info/PKG-INFO
src/plone.recipe.zope2install.egg-info/SOURCES.txt
src/plone.recipe.zope2install.egg-info/dependency_links.txt
src/plone.recipe.zope2install.egg-info/entry_points.txt
src/plone.recipe.zope2install.egg-info/namespace_packages.txt
src/plone.recipe.zope2install.egg-info/not-zip-safe
src/plone.recipe.zope2install.egg-info/requires.txt
src/plone.recipe.zope2install.egg-info/top_level.txt
src/plone/recipe/__init__.py
src/plone/recipe/zope2install/README.txt
src/plone/recipe/zope2install/__init__.py
src/plone/recipe/zope2install/tests/__init__.py
src/plone/recipe/zope2install/tests/test_docs.py