Metadata-Version: 1.0
Name: plone.recipe.zope2install
Version: 3.3
Summary: ZC Buildout recipe for installing Zope 2.
Home-page: http://svn.plone.org/svn/collective/buildout/plone.recipe.zope2install
Author: Hanno Schlichting
Author-email: hannosch@plone.org
License: ZPL 2.1
Keywords: zope2 buildout
Platform: UNKNOWN
Classifier: License :: OSI Approved :: Zope Public License
Classifier: Framework :: Buildout
Classifier: Framework :: Plone
Classifier: Framework :: Zope2
Classifier: Programming Language :: Python
